__init__.py
sdk_utils.py
tb_device_http.py
tb_device_mqtt.py
tb_gateway_mqtt.py
utils.py
ql_tb_mqtt_client-1.9.1.dist-info/licenses/LICENSE
ql_tb_mqtt_client-1.9.1.dist-info/METADATA
ql_tb_mqtt_client-1.9.1.dist-info/WHEEL
ql_tb_mqtt_client-1.9.1.dist-info/top_level.txt
ql_tb_mqtt_client-1.9.1.dist-info/RECORD
