Metadata-Version: 2.4
Name: ql-tb-mqtt-client
Version: 1.9.1
Summary: ThingsBoard python client SDK
Home-page: https://github.com/thingsboard/thingsboard-python-client-sdk
Download-URL: https://github.com/thingsboard/thingsboard-python-client-sdk/archive/1.9.1.tar.gz
Author: ThingsBoard
Author-email: info@thingsboard.io
License: Apache Software License (Apache Software License 2.0)
Requires-Python: >=3.7
License-File: LICENSE
Requires-Dist: tb-paho-mqtt-client>=1.6.3
Requires-Dist: requests>=2.31.0
Requires-Dist: simplejson
Dynamic: author
Dynamic: author-email
Dynamic: description
Dynamic: description-content-type
Dynamic: download-url
Dynamic: home-page
Dynamic: license
Dynamic: license-file
Dynamic: requires-dist
Dynamic: requires-python
Dynamic: summary
